pussycache
