Metadata-Version: 1.1
Name: pussycache
Version: 1.3
Summary: Cache Backend system for python objects
Home-page: https://github.com/novapost/pussycache
Author: Novapost Team
Author-email: peopleask@novapost.fr
License: BSD
Keywords: cache
Platform: UNKNOWN
Classifier: Development Status :: 4 - Beta
Classifier: License :: OSI Approved :: BSD License
Classifier: Programming Language :: Python :: 2.7
Classifier: Programming Language :: Python :: 2.6
Classifier: Framework :: Django
